CHANGES.txt
MANIFEST.in
README.rst
matcha.py
setup.py
matcha.egg-info/PKG-INFO
matcha.egg-info/SOURCES.txt
matcha.egg-info/dependency_links.txt
matcha.egg-info/top_level.txt